django_feather/__init__.py
django_feather/icons.py
django_feather/templatetags/__init__.py
django_feather/templatetags/icon.py
django_feather-0.3.0.dist-info/AUTHORS
django_feather-0.3.0.dist-info/LICENSE
django_feather-0.3.0.dist-info/METADATA
django_feather-0.3.0.dist-info/WHEEL
django_feather-0.3.0.dist-info/top_level.txt
django_feather-0.3.0.dist-info/RECORD
